setup.cfg
setup.py
sftp_s3_sync/__init__.py
sftp_s3_sync/sftp_api.py
sftp_s3_sync/sync_ftp_s3.py
sftp_s3_sync.egg-info/PKG-INFO
sftp_s3_sync.egg-info/SOURCES.txt
sftp_s3_sync.egg-info/dependency_links.txt
sftp_s3_sync.egg-info/not-zip-safe
sftp_s3_sync.egg-info/requires.txt
sftp_s3_sync.egg-info/top_level.txt