Metadata-Version: 1.1
Name: sftp-s3-sync
Version: 2.0.1
Summary: A python sftp and s3 syncing library
Home-page: https://github.com/parthz/sftp-s3-sync
Author: Partha
Author-email: parthasaradhi1992@gmail.com
License: UNKNOWN
Download-URL: https://github.com/parthz/sftp-s3-sync/tarball/0.1
Keywords: ftp sync s3,sftp sync s3
Platform: UNKNOWN
